jump_deps/__init__.py
jump_deps-0.0.7.dist-info/METADATA
jump_deps-0.0.7.dist-info/WHEEL
jump_deps-0.0.7.dist-info/RECORD
