Metadata-Version: 2.1
Name: jump_deps
Version: 0.0.7
Summary: Convenience package to add dependencies for JUMP exploratory analysis
Author: Alan Munoz
Requires-Python: >=3.10,<3.12
Classifier: Programming Language :: Python :: 3
Classifier: Programming Language :: Python :: 3.10
Classifier: Programming Language :: Python :: 3.11
Requires-Dist: biopython (>=1.84,<2.0)
Requires-Dist: boto3 (==1.34.131)
Requires-Dist: broad-babel (>=0.1.26)
Requires-Dist: copairs (>=0.4.1,<0.5.0)
Requires-Dist: ipdb (>=0.13.13,<0.14.0)
Requires-Dist: matplotlib (>=3.8.2,<4.0.0)
Requires-Dist: polars (>=1.5.0,<2.0.0)
Requires-Dist: pyarrow (>=15.0.0)
Requires-Dist: s3fs (>=2023.12.1)
Requires-Dist: seaborn (>=0.13.2,<0.14.0)
